mixer/__init__.py
mixer/cli.py
mixer/config.py
mixer/mixer.py
mixer/redis_store.py
mixer/rest.py
mixer/send_cc.py
mixer/utils.py
mixer/static/css/main.css
mixer/static/styles/base.css
mixer/templates/base.html
mixer/templates/mixer/mixer.html
midi_webmixer-0.0.1.dist-info/METADATA
midi_webmixer-0.0.1.dist-info/WHEEL
midi_webmixer-0.0.1.dist-info/entry_points.txt
midi_webmixer-0.0.1.dist-info/top_level.txt
midi_webmixer-0.0.1.dist-info/RECORD
